{
 "absolute_value": 0,
 "align_labels_right": 1,
 "creation": "2024-11-11 11:34:29.038329",
 "custom_format": 0,
 "default_print_language": "en",
 "disabled": 0,
 "doc_type": "Conference Ticket",
 "docstatus": 0,
 "doctype": "Print Format",
 "font": "Poppins",
 "font_size": 14,
 "format_data": "[{\"fieldname\": \"print_heading_template\", \"fieldtype\": \"Custom HTML\", \"options\": \"{% set conf = frappe.db.get_value(\\\"Conference Registration\\\", doc.registration, \\\"conference\\\") %}\\n\\n<div class=\\\"print-heading\\\">\\t\\t\\t\\t<h2><div>Ticket to {{ conf }}!</div><br><small class=\\\"sub-heading\\\">{{ doc.name }}</small>\\t\\t\\t\\t</h2></div>\"}, {\"fieldtype\": \"Section Break\", \"label\": \"\"}, {\"fieldtype\": \"Column Break\"}, {\"fieldname\": \"full_name\", \"print_hide\": 0, \"label\": \"Full Name\"}, {\"fieldname\": \"email\", \"print_hide\": 0, \"label\": \"Email\"}, {\"fieldname\": \"qr_code\", \"print_hide\": 0, \"label\": \"QR Code\"}, {\"fieldtype\": \"Column Break\"}, {\"fieldname\": \"ticket_type\", \"print_hide\": 0, \"label\": \"Ticket Type\"}]",
 "idx": 0,
 "line_breaks": 1,
 "margin_bottom": 15.0,
 "margin_left": 15.0,
 "margin_right": 15.0,
 "margin_top": 15.0,
 "modified": "2024-11-11 12:15:42.652200",
 "modified_by": "Administrator",
 "module": "Conference Management",
 "name": "Ticket Design",
 "owner": "Administrator",
 "page_number": "Hide",
 "print_format_builder": 0,
 "print_format_builder_beta": 0,
 "print_format_type": "Jinja",
 "raw_printing": 0,
 "show_section_headings": 1,
 "standard": "Yes"
}